<!--
 * Copyright 2012 Google Inc.
 *
 * Licensed under the Apache License, Version 2.0 (the "License"); you may not
 * use this file except in compliance with the License. You may obtain a copy of
 * the License at
 *
 * http://www.apache.org/licenses/LICENSE-2.0
 *
 * Unless required by applicable law or agreed to in writing, software
 * distributed under the License is distributed on an "AS IS" BASIS, WITHOUT
 * WARRANTIES OR CONDITIONS OF ANY KIND, either express or implied. See the
 * License for the specific language governing permissions and limitations under
 * the License.
-->
<idea-plugin version="2">

  <extensions defaultExtensionNs="com.intellij">
    <localInspection groupPath="JavaScript"
                     groupName="JsTestDriver"
                     displayName="Add JsTestDriver assertion framework support"
                     shortName="JstdAssertionFrameworkSupport"
                     enabledByDefault="true"
                     level="WARNING"
                     implementationClass="com.google.jstestdriver.idea.assertFramework.jstd.JstdAssertionFrameworkSupportInspection"
    />
    <localInspection groupPath="JavaScript"
                     groupName="JsTestDriver"
                     displayName="Add QUnit JsTestDriver adapter"
                     shortName="QUnitAdapterSupport"
                     enabledByDefault="true"
                     level="WARNING"
                     implementationClass="com.google.jstestdriver.idea.assertFramework.qunit.QUnitAdapterSupportInspection"
    />
    <localInspection groupPath="JavaScript"
                     groupName="JsTestDriver"
                     displayName="Add Jasmine JsTestDriver adapter"
                     shortName="JasmineAdapterSupport"
                     enabledByDefault="true"
                     level="WARNING"
                     implementationClass="com.google.jstestdriver.idea.assertFramework.jasmine.JasmineAdapterSupportInspection"
    />
    <localInspection groupPath="JavaScript"
                     groupName="JsTestDriver"
                     displayName="Reports about JsTestDriver TestCase without tests"
                     shortName="JsTestDriverTestCaseWithoutTests"
                     enabledByDefault="true"
                     level="WARNING"
                     implementationClass="com.google.jstestdriver.idea.assertFramework.jstd.JsTestDriverTestCaseWithoutTestsInspection"
    />

    <languageInjector implementation="com.google.jstestdriver.idea.assertFramework.jstd.JstdFixtureHtmlLanguageInjector"/>
    <codeInsight.lineMarkerProvider language="JavaScript" implementationClass="com.google.jstestdriver.idea.assertFramework.jstd.JstdAssertionFrameworkLineMarkerProvider"/>
    <implicitUsageProvider implementation="com.google.jstestdriver.idea.assertFramework.jstd.JstdImplicitUsageProvider"/>
  </extensions>

  <actions>
    <action id="JstdCreateTestAction" class="com.google.jstestdriver.idea.assertFramework.jstd.codeInsight.JstdGenerateNewTestAction"/>
    <action id="JstdCreateSetupAction" class="com.google.jstestdriver.idea.assertFramework.jstd.codeInsight.JstdGenerateSetupAction"/>
    <action id="JstdCreateTearDownAction"
            class="com.google.jstestdriver.idea.assertFramework.jstd.codeInsight.JstdGenerateTearDownAction"/>
  </actions>

</idea-plugin>
