<xml type="Scenario" name="Duplicate Line" passed="false" version="0.1" target="DuplicateLineDemo.java">
    <Start description="Want to learn how to duplicate lines of code?" btn="Yes!"/>
    <MouseBlock>
    <CopyText>public class DuplicateLineDemo {

    public static void main(String[] args) {

        int a = 7;
        double x = 0.34;

        //Let's find the absolute value of a and x.
        System.out.println("|" + a + "| is " + Math.abs(a));
    }
}</CopyText>
    <Text description="Let's print the absolute value of x" btn="...">Let's print the absolute value of &lt;span color="gray"&gt;x&lt;/span&gt;</Text>
    <TraverseCaret stop="178" delay="20"/>
    <Action action="EditorDuplicate" delay="2000" balloon="&lt;shortcut&gt; (Duplicate line)"/>
    <Wait delay="200"/>
    <TraverseCaret stop="271" delay="50"/>
    <Action action="EditorDelete" delay="100"/>
    <Wait delay="300"/>
    <TypeText>x</TypeText>
    <TraverseCaret stop="294" delay="10"/>
    <Action action="EditorDelete" delay="50" />
    <Wait delay="400"/>
    <TypeText>x</TypeText>
</MouseBlock>
    <Text description="That's it!" btn="Let me try"/>
    <Action action="EditorDelete" delay="50"/>
    <Action action="$SelectAll" delay="100"/>
    <Wait delay="400"/>
    <Action action="$Delete" delay="100"/>
    <Wait delay="400"/>
    <MoveCaret offset="0"/>
    <CopyText>public class DuplicateLineDemo {

    public static void main(String[] args) {

        int a = 7;
        double x = 0.34;

        //Let's find the absolute value of a and x.
        System.out.println("|" + a + "| is " + Math.abs(a));
    }
}</CopyText>
    <Try description="Duplicate print line and replace &lt;span color=&quot;gray&quot;&gt;a&lt;/span&gt; with &lt;span color=&quot;gray&quot;&gt;x&lt;/span&gt;" win-message="Perfect, now you know how to duplicate lines easily!" trigger="EditorDuplicate"/>
</xml>